{
    "model.layers.0.self_attn.q_proj": 603.158447265625,
    "model.layers.0.self_attn.k_proj": 603.849853515625,
    "model.layers.0.self_attn.v_proj": 644.258544921875,
    "model.layers.0.self_attn.o_proj": 604.5797729492188,
    "model.layers.0.mlp.gate_proj": 887.8955688476562,
    "model.layers.0.mlp.up_proj": 889.0183715820312,
    "model.layers.0.mlp.down_proj": 903.7822265625,
    "model.layers.1.self_attn.q_proj": 597.8441162109375,
    "model.layers.1.self_attn.k_proj": 603.2406616210938,
    "model.layers.1.self_attn.v_proj": 617.1637573242188,
    "model.layers.1.self_attn.o_proj": 585.7742919921875,
    "model.layers.1.mlp.gate_proj": 903.355712890625,
    "model.layers.1.mlp.up_proj": 904.8937377929688,
    "model.layers.1.mlp.down_proj": 906.4908447265625,
    "model.layers.2.self_attn.q_proj": 570.8312377929688,
    "model.layers.2.self_attn.k_proj": 628.8287353515625,
    "model.layers.2.self_attn.v_proj": 662.1332397460938,
    "model.layers.2.self_attn.o_proj": 616.6312255859375,
    "model.layers.2.mlp.gate_proj": 909.8914184570312,
    "model.layers.2.mlp.up_proj": 897.0747680664062,
    "model.layers.2.mlp.down_proj": 975.8153686523438,
    "model.layers.3.self_attn.q_proj": 614.7642822265625,
    "model.layers.3.self_attn.k_proj": 577.1326904296875,
    "model.layers.3.self_attn.v_proj": 637.0037231445312,
    "model.layers.3.self_attn.o_proj": 668.8418579101562,
    "model.layers.3.mlp.gate_proj": 903.560302734375,
    "model.layers.3.mlp.up_proj": 911.7326049804688,
    "model.layers.3.mlp.down_proj": 947.7431640625,
    "model.layers.4.self_attn.q_proj": 644.0772094726562,
    "model.layers.4.self_attn.k_proj": 597.9255981445312,
    "model.layers.4.self_attn.v_proj": 688.6370239257812,
    "model.layers.4.self_attn.o_proj": 641.5468139648438,
    "model.layers.4.mlp.gate_proj": 864.695556640625,
    "model.layers.4.mlp.up_proj": 918.6009521484375,
    "model.layers.4.mlp.down_proj": 888.0175170898438,
    "model.layers.5.self_attn.q_proj": 568.5394287109375,
    "model.layers.5.self_attn.k_proj": 636.428955078125,
    "model.layers.5.self_attn.v_proj": 693.6331787109375,
    "model.layers.5.self_attn.o_proj": 651.4561157226562,
    "model.layers.5.mlp.gate_proj": 934.0159301757812,
    "model.layers.5.mlp.up_proj": 866.29443359375,
    "model.layers.5.mlp.down_proj": 885.3646850585938,
    "model.layers.6.self_attn.q_proj": 527.0645751953125,
    "model.layers.6.self_attn.k_proj": 635.1474609375,
    "model.layers.6.self_attn.v_proj": 699.7234497070312,
    "model.layers.6.self_attn.o_proj": 612.0761108398438,
    "model.layers.6.mlp.gate_proj": 862.1414184570312,
    "model.layers.6.mlp.up_proj": 915.592529296875,
    "model.layers.6.mlp.down_proj": 906.514892578125,
    "model.layers.7.self_attn.q_proj": 635.18603515625,
    "model.layers.7.self_attn.k_proj": 684.7422485351562,
    "model.layers.7.self_attn.v_proj": 747.4732055664062,
    "model.layers.7.self_attn.o_proj": 608.9207763671875,
    "model.layers.7.mlp.gate_proj": 877.9468383789062,
    "model.layers.7.mlp.up_proj": 880.6116943359375,
    "model.layers.7.mlp.down_proj": 912.1397705078125,
    "model.layers.8.self_attn.q_proj": 635.3348388671875,
    "model.layers.8.self_attn.k_proj": 636.1605224609375,
    "model.layers.8.self_attn.v_proj": 722.658935546875,
    "model.layers.8.self_attn.o_proj": 632.7225341796875,
    "model.layers.8.mlp.gate_proj": 907.7513427734375,
    "model.layers.8.mlp.up_proj": 853.1132202148438,
    "model.layers.8.mlp.down_proj": 862.733154296875,
    "model.layers.9.self_attn.q_proj": 632.0835571289062,
    "model.layers.9.self_attn.k_proj": 650.8024291992188,
    "model.layers.9.self_attn.v_proj": 614.959228515625,
    "model.layers.9.self_attn.o_proj": 570.6021728515625,
    "model.layers.9.mlp.gate_proj": 896.5560302734375,
    "model.layers.9.mlp.up_proj": 895.4969482421875,
    "model.layers.9.mlp.down_proj": 877.7070922851562,
    "model.layers.10.self_attn.q_proj": 595.3772583007812,
    "model.layers.10.self_attn.k_proj": 684.087158203125,
    "model.layers.10.self_attn.v_proj": 579.8663940429688,
    "model.layers.10.self_attn.o_proj": 591.1724853515625,
    "model.layers.10.mlp.gate_proj": 916.7701416015625,
    "model.layers.10.mlp.up_proj": 851.2962036132812,
    "model.layers.10.mlp.down_proj": 918.9983520507812,
    "model.layers.11.self_attn.q_proj": 600.894775390625,
    "model.layers.11.self_attn.k_proj": 667.7523193359375,
    "model.layers.11.self_attn.v_proj": 631.8048706054688,
    "model.layers.11.self_attn.o_proj": 555.5150146484375,
    "model.layers.11.mlp.gate_proj": 891.9030151367188,
    "model.layers.11.mlp.up_proj": 889.3035888671875,
    "model.layers.11.mlp.down_proj": 873.0541381835938,
    "model.layers.12.self_attn.q_proj": 590.876953125,
    "model.layers.12.self_attn.k_proj": 621.3723754882812,
    "model.layers.12.self_attn.v_proj": 641.49609375,
    "model.layers.12.self_attn.o_proj": 565.64990234375,
    "model.layers.12.mlp.gate_proj": 909.5280151367188,
    "model.layers.12.mlp.up_proj": 846.5814208984375,
    "model.layers.12.mlp.down_proj": 893.5260009765625,
    "model.layers.13.self_attn.q_proj": 638.4590454101562,
    "model.layers.13.self_attn.k_proj": 626.6158447265625,
    "model.layers.13.self_attn.v_proj": 646.4724731445312,
    "model.layers.13.self_attn.o_proj": 600.0377807617188,
    "model.layers.13.mlp.gate_proj": 895.05712890625,
    "model.layers.13.mlp.up_proj": 892.8194580078125,
    "model.layers.13.mlp.down_proj": 928.4944458007812,
    "model.layers.14.self_attn.q_proj": 593.671142578125,
    "model.layers.14.self_attn.k_proj": 590.5964965820312,
    "model.layers.14.self_attn.v_proj": 630.844482421875,
    "model.layers.14.self_attn.o_proj": 548.013916015625,
    "model.layers.14.mlp.gate_proj": 881.504150390625,
    "model.layers.14.mlp.up_proj": 889.4030151367188,
    "model.layers.14.mlp.down_proj": 904.1017456054688,
    "model.layers.15.self_attn.q_proj": 608.269287109375,
    "model.layers.15.self_attn.k_proj": 648.2932739257812,
    "model.layers.15.self_attn.v_proj": 673.7786254882812,
    "model.layers.15.self_attn.o_proj": 610.8526611328125,
    "model.layers.15.mlp.gate_proj": 900.412109375,
    "model.layers.15.mlp.up_proj": 886.3283081054688,
    "model.layers.15.mlp.down_proj": 921.1641235351562,
    "model.layers.16.self_attn.q_proj": 618.2237548828125,
    "model.layers.16.self_attn.k_proj": 600.1007690429688,
    "model.layers.16.self_attn.v_proj": 669.068359375,
    "model.layers.16.self_attn.o_proj": 516.5855712890625,
    "model.layers.16.mlp.gate_proj": 888.9010009765625,
    "model.layers.16.mlp.up_proj": 895.9292602539062,
    "model.layers.16.mlp.down_proj": 924.0300903320312,
    "model.layers.17.self_attn.q_proj": 601.7265625,
    "model.layers.17.self_attn.k_proj": 618.2337646484375,
    "model.layers.17.self_attn.v_proj": 651.1823120117188,
    "model.layers.17.self_attn.o_proj": 569.9391479492188,
    "model.layers.17.mlp.gate_proj": 895.4058837890625,
    "model.layers.17.mlp.up_proj": 895.3025512695312,
    "model.layers.17.mlp.down_proj": 896.3421630859375,
    "model.layers.18.self_attn.q_proj": 604.1822509765625,
    "model.layers.18.self_attn.k_proj": 611.7261962890625,
    "model.layers.18.self_attn.v_proj": 654.4619750976562,
    "model.layers.18.self_attn.o_proj": 579.8433837890625,
    "model.layers.18.mlp.gate_proj": 884.2741088867188,
    "model.layers.18.mlp.up_proj": 897.0205688476562,
    "model.layers.18.mlp.down_proj": 926.5025024414062,
    "model.layers.19.self_attn.q_proj": 610.3707885742188,
    "model.layers.19.self_attn.k_proj": 592.6643676757812,
    "model.layers.19.self_attn.v_proj": 645.6395263671875,
    "model.layers.19.self_attn.o_proj": 599.7621459960938,
    "model.layers.19.mlp.gate_proj": 899.02783203125,
    "model.layers.19.mlp.up_proj": 892.83935546875,
    "model.layers.19.mlp.down_proj": 910.05029296875,
    "model.layers.20.self_attn.q_proj": 605.2402954101562,
    "model.layers.20.self_attn.k_proj": 596.0819091796875,
    "model.layers.20.self_attn.v_proj": 622.5548706054688,
    "model.layers.20.self_attn.o_proj": 546.4096069335938,
    "model.layers.20.mlp.gate_proj": 894.498291015625,
    "model.layers.20.mlp.up_proj": 889.4968872070312,
    "model.layers.20.mlp.down_proj": 890.4607543945312,
    "model.layers.21.self_attn.q_proj": 608.2357177734375,
    "model.layers.21.self_attn.k_proj": 590.9352416992188,
    "model.layers.21.self_attn.v_proj": 623.1528930664062,
    "model.layers.21.self_attn.o_proj": 570.7939453125,
    "model.layers.21.mlp.gate_proj": 891.0101928710938,
    "model.layers.21.mlp.up_proj": 888.1588745117188,
    "model.layers.21.mlp.down_proj": 909.5568237304688,
    "model.layers.22.self_attn.q_proj": 622.5635375976562,
    "model.layers.22.self_attn.k_proj": 604.6235961914062,
    "model.layers.22.self_attn.v_proj": 633.0538940429688,
    "model.layers.22.self_attn.o_proj": 561.8740234375,
    "model.layers.22.mlp.gate_proj": 891.302490234375,
    "model.layers.22.mlp.up_proj": 882.9996948242188,
    "model.layers.22.mlp.down_proj": 897.1535034179688,
    "model.layers.23.self_attn.q_proj": 598.8529052734375,
    "model.layers.23.self_attn.k_proj": 609.9021606445312,
    "model.layers.23.self_attn.v_proj": 627.3592529296875,
    "model.layers.23.self_attn.o_proj": 607.8724975585938,
    "model.layers.23.mlp.gate_proj": 891.8297119140625,
    "model.layers.23.mlp.up_proj": 886.8729248046875,
    "model.layers.23.mlp.down_proj": 899.64306640625,
    "model.layers.24.self_attn.q_proj": 603.3530883789062,
    "model.layers.24.self_attn.k_proj": 599.9310913085938,
    "model.layers.24.self_attn.v_proj": 605.4996337890625,
    "model.layers.24.self_attn.o_proj": 561.704345703125,
    "model.layers.24.mlp.gate_proj": 890.1424560546875,
    "model.layers.24.mlp.up_proj": 894.4927368164062,
    "model.layers.24.mlp.down_proj": 898.7954711914062,
    "model.layers.25.self_attn.q_proj": 608.5162353515625,
    "model.layers.25.self_attn.k_proj": 576.2962036132812,
    "model.layers.25.self_attn.v_proj": 601.1773681640625,
    "model.layers.25.self_attn.o_proj": 601.4545288085938,
    "model.layers.25.mlp.gate_proj": 887.5921020507812,
    "model.layers.25.mlp.up_proj": 900.0146484375,
    "model.layers.25.mlp.down_proj": 898.37548828125,
    "model.layers.26.self_attn.q_proj": 627.4856567382812,
    "model.layers.26.self_attn.k_proj": 602.0057983398438,
    "model.layers.26.self_attn.v_proj": 624.3963012695312,
    "model.layers.26.self_attn.o_proj": 609.30908203125,
    "model.layers.26.mlp.gate_proj": 879.8231201171875,
    "model.layers.26.mlp.up_proj": 891.7150268554688,
    "model.layers.26.mlp.down_proj": 902.9865112304688,
    "model.layers.27.self_attn.q_proj": 616.6109008789062,
    "model.layers.27.self_attn.k_proj": 628.6428833007812,
    "model.layers.27.self_attn.v_proj": 646.3972778320312,
    "model.layers.27.self_attn.o_proj": 637.6460571289062,
    "model.layers.27.mlp.gate_proj": 879.177734375,
    "model.layers.27.mlp.up_proj": 895.0897216796875,
    "model.layers.27.mlp.down_proj": 895.9712524414062,
    "model.layers.28.self_attn.q_proj": 623.2306518554688,
    "model.layers.28.self_attn.k_proj": 598.8076782226562,
    "model.layers.28.self_attn.v_proj": 593.0348510742188,
    "model.layers.28.self_attn.o_proj": 595.2159423828125,
    "model.layers.28.mlp.gate_proj": 875.3177490234375,
    "model.layers.28.mlp.up_proj": 905.1326904296875,
    "model.layers.28.mlp.down_proj": 916.01318359375,
    "model.layers.29.self_attn.q_proj": 609.31494140625,
    "model.layers.29.self_attn.k_proj": 579.8037109375,
    "model.layers.29.self_attn.v_proj": 618.3035278320312,
    "model.layers.29.self_attn.o_proj": 561.7075805664062,
    "model.layers.29.mlp.gate_proj": 765.185791015625,
    "model.layers.29.mlp.up_proj": 884.5343017578125,
    "model.layers.29.mlp.down_proj": 901.167236328125,
    "model.layers.30.self_attn.q_proj": 619.713134765625,
    "model.layers.30.self_attn.k_proj": 592.6318969726562,
    "model.layers.30.self_attn.v_proj": 630.4879150390625,
    "model.layers.30.self_attn.o_proj": 634.2399291992188,
    "model.layers.30.mlp.gate_proj": 884.6002197265625,
    "model.layers.30.mlp.up_proj": 908.4707641601562,
    "model.layers.30.mlp.down_proj": 891.9945068359375,
    "model.layers.31.self_attn.q_proj": 606.1576538085938,
    "model.layers.31.self_attn.k_proj": 579.6322021484375,
    "model.layers.31.self_attn.v_proj": 618.1328735351562,
    "model.layers.31.self_attn.o_proj": 668.3207397460938,
    "model.layers.31.mlp.gate_proj": 873.6146240234375,
    "model.layers.31.mlp.up_proj": 900.2206420898438,
    "model.layers.31.mlp.down_proj": 897.5643310546875,
    "ppl": [
        8.830948829650879,
        10.946467399597168,
        8.476829528808594,
        8.374423027038574,
        6.390527725219727
    ],
    "compression_ratio": 0.5999210476875305,
    "lr": 4.6112604669781785
}